aimodels/__init__.py
aimodels/models.py
aimodels_dev-0.3.13.dist-info/METADATA
aimodels_dev-0.3.13.dist-info/WHEEL
aimodels_dev-0.3.13.dist-info/RECORD
