Metadata-Version: 2.4
Name: aimodels.dev
Version: 0.3.13
Summary: A collection of AI model specifications across different providers
Project-URL: Homepage, https://github.com/mitkury/aimodels#readme
Project-URL: Repository, https://github.com/mitkury/aimodels.git
Project-URL: Issues, https://github.com/mitkury/aimodels/issues
Author-email: Dmitry Kury <d@dkury.com>
License-Expression: MIT
Keywords: ai,ai models,anthropic,llm,machine-learning,mistral,models,open-source,openai,specifications
Classifier: Development Status :: 3 - Alpha
Classifier: Intended Audience :: Developers
Classifier: License :: OSI Approved :: MIT License
Classifier: Programming Language :: Python :: 3
Classifier: Programming Language :: Python :: 3.8
Classifier: Programming Language :: Python :: 3.9
Classifier: Programming Language :: Python :: 3.10
Classifier: Programming Language :: Python :: 3.11
Requires-Python: >=3.8
Provides-Extra: dev
Requires-Dist: build>=1.0.0; extra == 'dev'
Requires-Dist: pytest>=7.0.0; extra == 'dev'
Requires-Dist: twine>=4.0.0; extra == 'dev'
